[
  {"id": "q001", "text": "Confia en Dios, aun cuando no entiendas el camino."},
  {"id": "q002", "text": "Nada te turbe, nada te espante; solo Dios basta."},
  {"id": "q003", "text": "Todo lo puedo en Cristo, que me fortalece."},
  {"id": "q004", "text": "No tengan miedo: el Señor camina a tu lado."},
  {"id": "q005", "text": "La fe no quita las tormentas, pero calma el corazon en medio de ellas."},
  {"id": "q006", "text": "Un pequeño acto de amor vale mas que muchas palabras."},
  {"id": "q007", "text": "Donde hay caridad y amor, alli esta Dios."},
  {"id": "q008", "text": "La oracion es la respiracion del alma."},
  {"id": "q009", "text": "Hoy es un buen dia para empezar de nuevo."},
  {"id": "q010", "text": "Dios no llama a los capacitados, capacita a los que llama."},
  {"id": "q011", "text": "En el silencio, Dios habla mas fuerte."},
  {"id": "q012", "text": "La paciencia es una oracion que se vive."},
  {"id": "q013", "text": "Cada amanecer es una nueva oportunidad de la gracia."},
  {"id": "q014", "text": "El amor de Dios no se mide, se recibe."},
  {"id": "q015", "text": "Ser agradecido transforma un dia comun en un regalo."},
  {"id": "q016", "text": "La esperanza es el ancla que sostiene el alma."},
  {"id": "q017", "text": "No estas solo: alguien reza por ti sin que lo sepas."},
  {"id": "q018", "text": "La humildad abre la puerta que el orgullo cierra."},
  {"id": "q019", "text": "Dios escribe derecho con lineas torcidas."},
  {"id": "q020", "text": "Sirve con alegria, aunque nadie lo note."},
  {"id": "q021", "text": "La fe pequeña, cuidada, mueve montañas."},
  {"id": "q022", "text": "Perdonar es liberar tu propio corazon."},
  {"id": "q023", "text": "Donde termina tu fuerza, empieza la de Dios."},
  {"id": "q024", "text": "Una vida agradecida es una vida en paz."},
  {"id": "q025", "text": "El amor verdadero se demuestra en lo pequeño."},
  {"id": "q026", "text": "La cruz de hoy prepara la alegria de mañana."},
  {"id": "q027", "text": "Buscar a Dios es ya haberlo encontrado un poco."},
  {"id": "q028", "text": "La sencillez del corazon agrada mas que las grandes palabras."},
  {"id": "q029", "text": "El que camina con Dios nunca camina solo."},
  {"id": "q030", "text": "Hoy, deja que la gracia te sorprenda."},
  {"id": "q031", "text": "Dios cuida de ti mas de lo que tu te preocupas por ti mismo."},
  {"id": "q032", "text": "El Señor esta cerca de los que tienen el corazon roto."},
  {"id": "q033", "text": "Reza como si todo dependiera de Dios; actua como si todo dependiera de ti."},
  {"id": "q034", "text": "Un corazon agradecido siempre encuentra motivos para sonreir."},
  {"id": "q035", "text": "La misericordia de Dios es nueva cada mañana."},
  {"id": "q036", "text": "No temas al mañana: Dios ya esta alli."},
  {"id": "q037", "text": "Ama y haz lo que quieras: si amas de verdad, haras el bien."},
  {"id": "q038", "text": "Las tormentas pasan; la Palabra de Dios permanece."},
  {"id": "q039", "text": "Tu oracion de hoy puede ser el milagro de alguien mañana."},
  {"id": "q040", "text": "La santidad se construye con pequeños pasos de cada dia."},
  {"id": "q041", "text": "Dios no promete un camino facil, promete caminar contigo."},
  {"id": "q042", "text": "Deja en manos de Dios lo que tus manos no pueden sostener."},
  {"id": "q043", "text": "La alegria es el eco de la vida de Dios en nosotros."},
  {"id": "q044", "text": "Quien reza el Rosario nunca camina sin su Madre."},
  {"id": "q045", "text": "El perdon no cambia el pasado, pero abre el futuro."},
  {"id": "q046", "text": "Se luz donde haya oscuridad, y paz donde haya conflicto."},
  {"id": "q047", "text": "Dios habla en el susurro suave, no siempre en el trueno."},
  {"id": "q048", "text": "Cada persona que encuentras hoy es una oportunidad de amar."},
  {"id": "q049", "text": "La paz empieza con una sonrisa."},
  {"id": "q050", "text": "Confia en los tiempos de Dios: nunca llega tarde."},
  {"id": "q051", "text": "El cielo se conquista con amor, no con perfeccion."},
  {"id": "q052", "text": "Tu historia con Dios apenas esta comenzando."},
  {"id": "q053", "text": "Entrega tus cargas: los hombros de Dios son mas fuertes."},
  {"id": "q054", "text": "La gratitud convierte lo poco en suficiente."},
  {"id": "q055", "text": "Se paciente contigo mismo: Dios aun no termina su obra en ti."},
  {"id": "q056", "text": "Vive este dia como un regalo, porque eso es."},
  {"id": "q057", "text": "El amor de Dios te busca incluso cuando tu no lo buscas."},
  {"id": "q058", "text": "Siembra bondad: la cosecha llegara a su tiempo."},
  {"id": "q059", "text": "En cada eucaristia, el cielo toca la tierra."},
  {"id": "q060", "text": "No cuentes tus problemas: cuentale a Dios tus problemas."}
]
